AUTHORS
MANIFEST.in
README.rst
runtests.py
setup.py
django_lifestreams.egg-info/PKG-INFO
django_lifestreams.egg-info/SOURCES.txt
django_lifestreams.egg-info/dependency_links.txt
django_lifestreams.egg-info/requires.txt
django_lifestreams.egg-info/top_level.txt
django_lifestreams.egg-info/zip-safe
lifestreams/__init__.py
lifestreams/admin.py
lifestreams/exceptions.py
lifestreams/models.py
lifestreams/tests.py
lifestreams/utils.py
lifestreams/views.py
lifestreams/management/__init__.py
lifestreams/management/commands/__init__.py
lifestreams/management/commands/update_lifestreams.py
lifestreams/plugins/__init__.py
lifestreams/plugins/lifestream_instagram/__init__.py
lifestreams/plugins/lifestream_instagram/admin.py
lifestreams/plugins/lifestream_instagram/models.py
lifestreams/plugins/lifestream_instagram/plugin.py
lifestreams/plugins/lifestream_instagram/tests.py
lifestreams/plugins/lifestream_instagram/views.py
lifestreams/plugins/lifestream_rss/__init__.py
lifestreams/plugins/lifestream_rss/admin.py
lifestreams/plugins/lifestream_rss/models.py
lifestreams/plugins/lifestream_rss/plugin.py
lifestreams/plugins/lifestream_rss/tests.py
lifestreams/plugins/lifestream_rss/views.py
lifestreams/plugins/lifestream_twitter/__init__.py
lifestreams/plugins/lifestream_twitter/admin.py
lifestreams/plugins/lifestream_twitter/models.py
lifestreams/plugins/lifestream_twitter/plugin.py
lifestreams/plugins/lifestream_twitter/tests.py
lifestreams/plugins/lifestream_twitter/views.py
lifestreams/templatetags/__init__.py
lifestreams/templatetags/lifestream_tags.py