Metadata-Version: 1.1
Name: django-lifestreams
Version: 0.1.1
Summary: A lifestreams application for Django
Home-page: http://github.com/witoi/django-lifestreams
Author: Pedro Buron
Author-email: pedro@witoi.com
License: UNKNOWN
Platform: UNKNOWN
Classifier: Development Status :: 3 - Alpha
Classifier: Environment :: Plugins
Classifier: Framework :: Django
Classifier: Intended Audience :: Developers
Classifier: Programming Language :: Python
Classifier: Topic :: Software Development :: Libraries :: Python Modules
